{"kind":"Article","sha256":"c2c24ebe2100a2490fcddb2e430985528e65e316a3c620229f41a704c5be33f7","slug":"2023-03-17-crop-yield-first-results","location":"/results/2023-03-17-Crop-Yield-First-Results.md","dependencies":[],"frontmatter":{"title":"First results regarding crop yield and its relation with ET","content_includes_title":false,"open_access":true,"license":{"content":{"id":"CC-BY-4.0","name":"Creative Commons Attribution 4.0 International","free":true,"CC":true,"url":"https://creativecommons.org/licenses/by/4.0/"}},"exports":[{"format":"md","filename":"2023-03-17-Crop-Yield-First-Results.md","url":"/2023-03-17-Crop-Yiel-56691296b78ba0afe0b40a445325ce46.md"}]},"mdast":{"type":"root","children":[{"type":"block","children":[{"type":"paragraph","position":{"start":{"line":3,"column":1},"end":{"line":3,"column":1}},"children":[{"type":"text","value":"First tests using crop model simulations showed promising results in predicting wheat yield based on the actual vs. potential evapotranspiration deficit and peak biomass.","position":{"start":{"line":3,"column":1},"end":{"line":3,"column":1}},"key":"V5h7huM2Bh"}],"key":"lKCcZfz4Ci"}],"key":"hluO5QXEc5"}],"key":"dUZzggvW7B"},"references":{"cite":{"order":[],"data":{}}}}